proto/__init__.py
proto/alliance_pb2.py
proto/alliance_pb2_grpc.py
scaleout_proto-0.0.2.dist-info/LICENSE
scaleout_proto-0.0.2.dist-info/METADATA
scaleout_proto-0.0.2.dist-info/WHEEL
scaleout_proto-0.0.2.dist-info/top_level.txt
scaleout_proto-0.0.2.dist-info/RECORD
