Metadata-Version: 2.1
Name: scaleout-proto
Version: 0.0.2
Summary: Scaleout proto
Home-page: https://www.scaleoutsystems.com
Author: Morgan Ekmefjord
Author-email: morgan@scaleoutsystems.com
License: Copyright Scaleout Systems AB. See license for details
Platform: UNKNOWN
Classifier: Development Status :: 2 - Pre-Alpha
Classifier: Intended Audience :: Developers
Classifier: Natural Language :: English
Classifier: Programming Language :: Python :: 3
Classifier: Programming Language :: Python :: 3.5
Classifier: Programming Language :: Python :: 3.6
Requires-Python: >=3.5,<4
Requires-Dist: grpc-tools (==0.0.1)
Requires-Dist: grpcio (==1.27.1)
Requires-Dist: six (==1.14.0)
Requires-Dist: protobuf (==3.11.3)
Requires-Dist: pypandoc
Requires-Dist: wheel
